package_name/__init__.py
kahoot_api-1.0.0.dist-info/METADATA
kahoot_api-1.0.0.dist-info/WHEEL
kahoot_api-1.0.0.dist-info/top_level.txt
kahoot_api-1.0.0.dist-info/RECORD
